<?xml version="1.0" standalone="yes"?>
<DsMultidatos xmlns="PELOSCALVO">
  <DtArchivoDatosMulti>
    <Id>1</Id>
    <NombreArchivoDatos>Archivo Inicial</NombreArchivoDatos>
    <DirectorioArchivoDatos>C:\Users\Victor Pais\Desktop\Nueva carpeta</DirectorioArchivoDatos>
    <DescripcionArchivoDatos>Guarda Datos Aplicacion Principal</DescripcionArchivoDatos>
  </DtArchivoDatosMulti>
  <DtArchivoDatosMulti>
    <Id>2</Id>
    <NombreArchivoDatos>FDGDFGDFGF</NombreArchivoDatos>
    <DirectorioArchivoDatos>C:\AB\GestionApp\PELOSCALVO\bin\Debug</DirectorioArchivoDatos>
    <DescripcionArchivoDatos>Archivo de Datos Nuevo </DescripcionArchivoDatos>
  </DtArchivoDatosMulti>
  <DtInicioMulti>
    <ArchivoInicioFacturas>C:\AB\GestionApp\PELOSCALVO\bin\Debug\Datos\Configuracion.Xml</ArchivoInicioFacturas>
    <NombreArchivoDatos>FDGDFGDFGF</NombreArchivoDatos>
    <RutaArchivoDatos>C:\AB\GestionApp\PELOSCALVO\bin\Debug</RutaArchivoDatos>
  </DtInicioMulti>
  <DtPaises>
    <PaisesPaises>AA</PaisesPaises>
  </DtPaises>
  <DtPaises>
    <PaisesPaises>dsfsdf</PaisesPaises>
  </DtPaises>
  <DtPaises>
    <PaisesPaises>a</PaisesPaises>
  </DtPaises>
  <DtProvincias>
    <ProvinciasProvincias>fsdfsdfsd</ProvinciasProvincias>
  </DtProvincias>
  <DtProvincias>
    <ProvinciasProvincias>sdfsd</ProvinciasProvincias>
  </DtProvincias>
</DsMultidatos>